MANIFEST.in
setup.py
incuna_news.egg-info/PKG-INFO
incuna_news.egg-info/SOURCES.txt
incuna_news.egg-info/dependency_links.txt
incuna_news.egg-info/requires.txt
incuna_news.egg-info/top_level.txt
news/__init__.py
news/admin.py
news/feeds.py
news/models.py
news/urls.py
news/views.py
news/migrations/0001_initial.py
news/migrations/0002_auto__add_field_entry_tags.py
news/migrations/0003_added_category.py
news/migrations/__init__.py
news/templates/news/base.html
news/templates/news/entry_archive.html
news/templates/news/entry_archive_day.html
news/templates/news/entry_archive_month.html
news/templates/news/entry_archive_year.html
news/templates/news/entry_detail.html
news/templates/news/entry_list.html
news/templates/news/latest-entries.html
news/templatetags/__init__.py
news/templatetags/news_extras.py