Metadata-Version: 1.0
Name: incuna-news
Version: 1.3
Summary: Provides news.
Home-page: http://incuna.com/
Author: Incuna Ltd
Author-email: admin@incuna.com
License: UNKNOWN
Platform: UNKNOWN
